yamapan/__init__.py
yamapan/__main__.py
yamapan/alias.py
yamapan/build.py
yamapan/clean.py
yamapan/config.py
yamapan/init.py
yamapan/resolve.py
yamapan/ros2.py
yamapan/rqt.py
yamapan/util.py
yamapan-0.0.5.dist-info/METADATA
yamapan-0.0.5.dist-info/WHEEL
yamapan-0.0.5.dist-info/entry_points.txt
yamapan-0.0.5.dist-info/licenses/LICENSE
yamapan-0.0.5.dist-info/RECORD
