Metadata-Version: 2.3
Name: yamapan
Version: 0.0.5
Summary: Yet Another MetA worksPAce maNager for ROS 2
Project-URL: Repository, https://github.com/tutrobo/yamapan.git
Author-email: Rin Iwai <rin@eyrin.jp>
License:                                  Apache License
License-File: LICENSE
Requires-Python: >=3.8
Requires-Dist: pydantic>=2.7.1
Requires-Dist: pyyaml>=6.0.1
Requires-Dist: tomli>=2.0.1
